odoo/addons/l10n_us_gaap/README.rst
odoo/addons/l10n_us_gaap/__init__.py
odoo/addons/l10n_us_gaap/__manifest__.py
odoo/addons/l10n_us_gaap/data/account_chart_template_data.xml
odoo/addons/l10n_us_gaap/data/account_chart_template_data.yml
odoo/addons/l10n_us_gaap/data/account_group.xml
odoo/addons/l10n_us_gaap/data/account_us_gaap_data.xml
odoo/addons/l10n_us_gaap/data/res_company_data.xml
odoo/addons/l10n_us_gaap/docs/l10n_us_gaap_trial_balance.ods
odoo/addons/l10n_us_gaap/static/description/icon.png
odoo/addons/l10n_us_gaap/views/res_partner_bank_views.xml
odoo11_addon_l10n_us_gaap-11.0.1.0.0.dist-info/DESCRIPTION.rst
odoo11_addon_l10n_us_gaap-11.0.1.0.0.dist-info/METADATA
odoo11_addon_l10n_us_gaap-11.0.1.0.0.dist-info/RECORD
odoo11_addon_l10n_us_gaap-11.0.1.0.0.dist-info/WHEEL
odoo11_addon_l10n_us_gaap-11.0.1.0.0.dist-info/metadata.json
odoo11_addon_l10n_us_gaap-11.0.1.0.0.dist-info/top_level.txt
